{
  "base_price": 3750,
  "beamstation_catalog_url": "https://beamstation.com/datasets",
  "beamstation_origin": "https://beamstation.com",
  "category_group_name": "Restaurants",
  "config_category": "census",
  "config_description": "Complete restaurant data for the Greater Phoenix metro area including Mesa and Chandler. Covers the rapidly expanding Arizona dining market, filtered by the Restaurants category group. Includes business profiles, ratings, review trends, competitive metrics, and contact information. Refreshed weekly.",
  "config_name": "All Restaurants in Greater Phoenix Area (Metro), Arizona, US",
  "export_job_id": "07ff6193-d44b-41b4-a3d8-785398b5480c",
  "github_org": "Beamstation-Datasets",
  "id_short": 493317,
  "location_name": "Phoenix-Mesa-Chandler, AZ",
  "location_type": "metro",
  "repo_name": "all-restaurants-in-greater-phoenix-area-metro-arizona-us-sample-493317",
  "sample_b2_path": "b2-export:BeamStation-ExportFiles/493317/beamstation_493317_restaurants-us-phoenixmesachandleraz_SAMPLE_DIST.csv",
  "sample_pct": 9.53,
  "sample_records": 1000,
  "sample_sha256": "38c91f62e065de708a46474ac53cb1c099fd4cbc5160358ca1c15c37a2de1853",
  "sample_size_bytes": 3182213,
  "total_records": 10494,
  "updated_at": "2026-04-28T18:26:12.545666+00:00"
}